{
  "voc_eval_res": {
    "precision": 29.697,
    "recall": 48.5149,
    "f-score": 36.8421
  },
  "KL_res": {
    "KL divergence": 0.9300062575779199,
    "Euclidean Dist.": 0.30073695411714246,
    "WER": 2.763239875389408,
    "CER": 2.381855670103093,
    "Cosine Dist.": 0.02761380431502114
  },
  "occ_eval_res": {
    "precision": 23.1764,
    "recall": 78.1931,
    "f-score": 35.755
  },
  "clean_eval": {
    "f-score": 21.958456973293767,
    "precision": 47.896440129449836,
    "recall": 14.244465832531281,
    "tp": 148,
    "fp": 161,
    "fn": 891
  },
  "jaccard": [
    0.5571517801374141
  ],
  "braycurtis": [
    0.557124261540002
  ],
  "dice": [
    0.38614718614718613
  ],
  "cosinus": [
    0.05103924864242804
  ]
}