{
  "entite_0": {
    "label": "MISC",
    "text": "Gallica  Le département de l'Oise",
    "jalons": [
      6,
      39
    ]
  },
  "entite_1": {
    "label": "PER",
    "text": "Alexandre Sorel",
    "jalons": [
      93,
      108
    ]
  },
  "entite_2": {
    "label": "LOC",
    "text": "Bibliothèques de la Ville de Compiègne",
    "jalons": [
      137,
      175
    ]
  },
  "entite_3": {
    "label": "ORG",
    "text": "Gallica     de l'Oise",
    "jalons": [
      181,
      202
    ]
  },
  "entite_4": {
    "label": "MISC",
    "text": "Compiègne et Marat",
    "jalons": [
      205,
      223
    ]
  },
  "entite_5": {
    "label": "LOC",
    "text": "Sorel",
    "jalons": [
      257,
      262
    ]
  },
  "entite_6": {
    "label": "PER",
    "text": "Alexandre",
    "jalons": [
      264,
      273
    ]
  },
  "entite_7": {
    "label": "MISC",
    "text": "Auteur du texte",
    "jalons": [
      287,
      302
    ]
  },
  "entite_8": {
    "label": "PER",
    "text": "Alexandre Sorel",
    "jalons": [
      319,
      334
    ]
  },
  "entite_9": {
    "label": "LOC",
    "text": "France",
    "jalons": [
      420,
      426
    ]
  },
  "entite_10": {
    "label": "MISC",
    "text": "nus de Gallica sont la propriété de la BnF au sens de",
    "jalons": [
      0,
      53
    ]
  },
  "entite_11": {
    "label": "LOC",
    "text": "la loi français",
    "jalons": [
      497,
      512
    ]
  },
  "entite_12": {
    "label": "PER",
    "text": "ALEXANDRE SOREL",
    "jalons": [
      127,
      142
    ]
  },
  "entite_13": {
    "label": "MISC",
    "text": "‘AVocat à la Cour impériale de ‘",
    "jalons": [
      144,
      176
    ]
  },
  "entite_14": {
    "label": "LOC",
    "text": "Paris",
    "jalons": [
      176,
      181
    ]
  },
  "entite_15": {
    "label": "MISC",
    "text": "Dot de te Ses the IUT Le ou",
    "jalons": [
      213,
      240
    ]
  },
  "entite_16": {
    "label": "LOC",
    "text": "ARRAS",
    "jalons": [
      483,
      488
    ]
  },
  "entite_17": {
    "label": "ORG",
    "text": "DE L'IMPRIMERIE ROUSSE",
    "jalons": [
      490,
      512
    ]
  },
  "entite_18": {
    "label": "MISC",
    "text": "PENDANT LA REVOLUTION  COMPIÈGNE ET MARAT",
    "jalons": [
      111,
      152
    ]
  },
  "entite_19": {
    "label": "MISC",
    "text": "Chacun sait le rôle",
    "jalons": [
      180,
      199
    ]
  },
  "entite_20": {
    "label": "LOC",
    "text": "Paris",
    "jalons": [
      221,
      226
    ]
  },
  "entite_21": {
    "label": "MISC",
    "text": "la société des Amis de la Constitution qui",
    "jalons": [
      266,
      308
    ]
  },
  "entite_22": {
    "label": "MISC",
    "text": "le nom de Société des Jacobins",
    "jalons": [
      326,
      356
    ]
  },
  "entite_23": {
    "label": "MISC",
    "text": "Fondée dès le début de la",
    "jalons": [
      358,
      383
    ]
  },
  "entite_24": {
    "label": "LOC",
    "text": "France",
    "jalons": [
      468,
      474
    ]
  },
  "entite_25": {
    "label": "LOC",
    "text": "Compiègne",
    "jalons": [
      496,
      505
    ]
  },
  "entite_26": {
    "label": "MISC",
    "text": "Amis de la Constitution. La feuille sur laquelle",
    "jalons": [
      96,
      144
    ]
  },
  "entite_27": {
    "label": "MISC",
    "text": "Liste des citoyens qui doivent composer la société des Amis de la « Constitution",
    "jalons": [
      207,
      287
    ]
  },
  "entite_28": {
    "label": "MISC",
    "text": "des rôles de la nouvelle Contribution",
    "jalons": [
      0,
      37
    ]
  },
  "entite_29": {
    "label": "LOC",
    "text": "de la Société des Amis de la",
    "jalons": [
      196,
      224
    ]
  },
  "entite_30": {
    "label": "MISC",
    "text": "Constitution de Compiègne depuis le",
    "jalons": [
      225,
      260
    ]
  },
  "entite_31": {
    "label": "LOC",
    "text": "la ville de Compiègne",
    "jalons": [
      156,
      177
    ]
  },
  "entite_32": {
    "label": "PER",
    "text": "Réimpression du Moniteur",
    "jalons": [
      183,
      207
    ]
  },
  "entite_33": {
    "label": "PER",
    "text": "M. Tribale",
    "jalons": [
      297,
      307
    ]
  },
  "entite_34": {
    "label": "PER",
    "text": "alors maire de la ville",
    "jalons": [
      309,
      332
    ]
  },
  "entite_35": {
    "label": "PER",
    "text": "Stanislas Leféron",
    "jalons": [
      439,
      456
    ]
  },
  "entite_36": {
    "label": "MISC",
    "text": "Dans cette première réunion",
    "jalons": [
      459,
      486
    ]
  },
  "entite_37": {
    "label": "MISC",
    "text": "prendrait le nom de Société des Amis de la",
    "jalons": [
      2,
      44
    ]
  },
  "entite_38": {
    "label": "LOC",
    "text": "Mirabeau",
    "jalons": [
      416,
      424
    ]
  },
  "entite_39": {
    "label": "MISC",
    "text": "la société des amis de la Constitution de Noyon",
    "jalons": [
      126,
      173
    ]
  },
  "entite_40": {
    "label": "LOC",
    "text": "Compiègne",
    "jalons": [
      226,
      235
    ]
  },
  "entite_41": {
    "label": "MISC",
    "text": "Messieurs de Noyon et de les « assurer de",
    "jalons": [
      306,
      347
    ]
  },
  "entite_42": {
    "label": "LOC",
    "text": "Pénétrée de",
    "jalons": [
      110,
      121
    ]
  },
  "entite_43": {
    "label": "MISC",
    "text": "clairera sur les vrais principes de la Constitution",
    "jalons": [
      135,
      186
    ]
  },
  "entite_44": {
    "label": "MISC",
    "text": "celle des Jda- coins de Paris et à celle de Beauvais",
    "jalons": [
      43,
      95
    ]
  },
  "entite_45": {
    "label": "PER",
    "text": "Massieu",
    "jalons": [
      154,
      161
    ]
  },
  "entite_46": {
    "label": "LOC",
    "text": "de la part des amis de la Constitution de Noyon",
    "jalons": [
      429,
      476
    ]
  },
  "entite_47": {
    "label": "MISC",
    "text": "urs frères de Compiègne de les",
    "jalons": [
      0,
      30
    ]
  },
  "entite_48": {
    "label": "MISC",
    "text": "Jacobins de Paris",
    "jalons": [
      65,
      82
    ]
  },
  "entite_49": {
    "label": "LOC",
    "text": "Jean-Jacques-Rousseau",
    "jalons": [
      481,
      502
    ]
  },
  "entite_50": {
    "label": "LOC",
    "text": "Rainville",
    "jalons": [
      318,
      327
    ]
  },
  "entite_51": {
    "label": "LOC",
    "text": "du curé de Noyon",
    "jalons": [
      332,
      348
    ]
  },
  "entite_52": {
    "label": "LOC",
    "text": "Gibert",
    "jalons": [
      350,
      356
    ]
  },
  "entite_53": {
    "label": "PER",
    "text": "M. l'évêque",
    "jalons": [
      500,
      511
    ]
  },
  "entite_54": {
    "label": "PER",
    "text": "Massieu",
    "jalons": [
      63,
      70
    ]
  },
  "entite_55": {
    "label": "LOC",
    "text": "Givet",
    "jalons": [
      265,
      270
    ]
  },
  "entite_56": {
    "label": "LOC",
    "text": "Bruxelles",
    "jalons": [
      284,
      293
    ]
  },
  "entite_57": {
    "label": "LOC",
    "text": "Massieu",
    "jalons": [
      473,
      480
    ]
  },
  "entite_58": {
    "label": "PER",
    "text": "Libert de la",
    "jalons": [
      69,
      81
    ]
  },
  "entite_59": {
    "label": "MISC",
    "text": "présence dans la ville de Compiègne et « les assura aussi de l'opinion qu'on",
    "jalons": [
      122,
      198
    ]
  },
  "entite_60": {
    "label": "PER",
    "text": "Louis-Joseph-Stanislas Leféron",
    "jalons": [
      412,
      442
    ]
  },
  "entite_61": {
    "label": "LOC",
    "text": "Aussitô",
    "jalons": [
      505,
      512
    ]
  },
  "entite_62": {
    "label": "LOC",
    "text": "Bertrand",
    "jalons": [
      162,
      170
    ]
  },
  "entite_63": {
    "label": "LOC",
    "text": "Chabanon",
    "jalons": [
      190,
      198
    ]
  },
  "entite_64": {
    "label": "MISC",
    "text": "français en l'honneur du commandant et à rédiger une",
    "jalons": [
      45,
      97
    ]
  },
  "entite_65": {
    "label": "LOC",
    "text": "Paris",
    "jalons": [
      463,
      468
    ]
  },
  "entite_66": {
    "label": "ORG",
    "text": "la Constitution",
    "jalons": [
      491,
      506
    ]
  },
  "entite_67": {
    "label": "PER",
    "text": "Auss",
    "jalons": [
      508,
      512
    ]
  },
  "entite_68": {
    "label": "LOC",
    "text": "bonheur et de celui de la",
    "jalons": [
      384,
      409
    ]
  },
  "entite_69": {
    "label": "LOC",
    "text": "Toutefois",
    "jalons": [
      423,
      432
    ]
  },
  "entite_70": {
    "label": "MISC",
    "text": "des Amis de la Constitution de Compiègne s'amoindris",
    "jalons": [
      2,
      54
    ]
  },
  "entite_71": {
    "label": "PER",
    "text": "Thibaut",
    "jalons": [
      371,
      378
    ]
  },
  "entite_72": {
    "label": "LOC",
    "text": "Berger",
    "jalons": [
      380,
      386
    ]
  },
  "entite_73": {
    "label": "LOC",
    "text": "Saiget",
    "jalons": [
      388,
      394
    ]
  },
  "entite_74": {
    "label": "MISC",
    "text": "Chauffour",
    "jalons": [
      396,
      405
    ]
  },
  "entite_75": {
    "label": "MISC",
    "text": "Wattelet",
    "jalons": [
      407,
      415
    ]
  },
  "entite_76": {
    "label": "LOC",
    "text": "Mercier",
    "jalons": [
      417,
      424
    ]
  },
  "entite_77": {
    "label": "LOC",
    "text": "Courtois",
    "jalons": [
      426,
      434
    ]
  },
  "entite_78": {
    "label": "MISC",
    "text": "Lambin",
    "jalons": [
      436,
      442
    ]
  },
  "entite_79": {
    "label": "PER",
    "text": "Veron",
    "jalons": [
      444,
      449
    ]
  },
  "entite_80": {
    "label": "LOC",
    "text": "Rey",
    "jalons": [
      451,
      454
    ]
  },
  "entite_81": {
    "label": "LOC",
    "text": "Beaugrand",
    "jalons": [
      456,
      465
    ]
  },
  "entite_82": {
    "label": "ORG",
    "text": "Chambon et Monies",
    "jalons": [
      467,
      484
    ]
  },
  "entite_83": {
    "label": "LOC",
    "text": "Thi",
    "jalons": [
      71,
      74
    ]
  },
  "entite_84": {
    "label": "PER",
    "text": "Étienne Poulain",
    "jalons": [
      84,
      99
    ]
  },
  "entite_85": {
    "label": "LOC",
    "text": "la Société des Amis de la Constitution de cette ville",
    "jalons": [
      125,
      178
    ]
  },
  "entite_86": {
    "label": "LOC",
    "text": "nom de société d'Amis de la République",
    "jalons": [
      396,
      434
    ]
  },
  "entite_87": {
    "label": "LOC",
    "text": "de la société des Amis de la Cons",
    "jalons": [
      479,
      512
    ]
  },
  "entite_88": {
    "label": "MISC",
    "text": "Amis de la République",
    "jalons": [
      45,
      66
    ]
  },
  "entite_89": {
    "label": "LOC",
    "text": "Ens",
    "jalons": [
      509,
      512
    ]
  },
  "entite_90": {
    "label": "LOC",
    "text": "le couvent de Sainte",
    "jalons": [
      29,
      49
    ]
  },
  "entite_91": {
    "label": "LOC",
    "text": "Compiègne la nouvelle société des Amis de la République",
    "jalons": [
      174,
      229
    ]
  },
  "entite_92": {
    "label": "LOC",
    "text": "Dès la",
    "jalons": [
      232,
      238
    ]
  },
  "entite_93": {
    "label": "LOC",
    "text": "Paris",
    "jalons": [
      486,
      491
    ]
  },
  "entite_94": {
    "label": "MISC",
    "text": "la Révolution qui avait débarrassé la France des « rois et de La royauté",
    "jalons": [
      42,
      114
    ]
  },
  "entite_95": {
    "label": "LOC",
    "text": "de la Savoie du",
    "jalons": [
      127,
      142
    ]
  },
  "entite_96": {
    "label": "LOC",
    "text": "Marseillais",
    "jalons": [
      421,
      432
    ]
  },
  "entite_97": {
    "label": "ORG",
    "text": "de Montagnard",
    "jalons": [
      498,
      511
    ]
  },
  "entite_98": {
    "label": "LOC",
    "text": "Le nom de la",
    "jalons": [
      388,
      400
    ]
  },
  "entite_99": {
    "label": "PER",
    "text": "M. Lambert de Ballyhier",
    "jalons": [
      439,
      462
    ]
  },
  "entite_100": {
    "label": "LOC",
    "text": "Compiègne",
    "jalons": [
      490,
      499
    ]
  },
  "entite_101": {
    "label": "LOC",
    "text": "Nord",
    "jalons": [
      195,
      199
    ]
  },
  "entite_102": {
    "label": "ORG",
    "text": "nom de tous les citoyens de Compiègne",
    "jalons": [
      412,
      449
    ]
  },
  "entite_103": {
    "label": "MISC",
    "text": "Vive Louis XVII",
    "jalons": [
      268,
      283
    ]
  },
  "entite_104": {
    "label": "LOC",
    "text": "Marat sur La société des Amis de la République de Compiègne",
    "jalons": [
      400,
      459
    ]
  },
  "entite_105": {
    "label": "LOC",
    "text": "Publiciste de la République",
    "jalons": [
      482,
      509
    ]
  },
  "entite_106": {
    "label": "LOC",
    "text": "de la République",
    "jalons": [
      216,
      232
    ]
  },
  "entite_107": {
    "label": "LOC",
    "text": "de la République",
    "jalons": [
      428,
      444
    ]
  },
  "entite_108": {
    "label": "LOC",
    "text": "de la Conven",
    "jalons": [
      500,
      512
    ]
  },
  "entite_109": {
    "label": "MISC",
    "text": "séance du lundi",
    "jalons": [
      6,
      21
    ]
  },
  "entite_110": {
    "label": "MISC",
    "text": "l'armée qui va réduire les rebelles dans le département de Mayenne et",
    "jalons": [
      79,
      148
    ]
  },
  "entite_111": {
    "label": "LOC",
    "text": "Loire",
    "jalons": [
      150,
      155
    ]
  },
  "entite_112": {
    "label": "LOC",
    "text": "Ourscamp",
    "jalons": [
      162,
      170
    ]
  },
  "entite_113": {
    "label": "LOC",
    "text": "Paris",
    "jalons": [
      227,
      232
    ]
  },
  "entite_114": {
    "label": "LOC",
    "text": "de la Montagne",
    "jalons": [
      226,
      240
    ]
  },
  "entite_115": {
    "label": "LOC",
    "text": "Paris",
    "jalons": [
      329,
      334
    ]
  },
  "entite_116": {
    "label": "LOC",
    "text": "Prenez",
    "jalons": [
      109,
      115
    ]
  },
  "entite_117": {
    "label": "LOC",
    "text": "Compiègne",
    "jalons": [
      419,
      428
    ]
  },
  "entite_118": {
    "label": "MISC",
    "text": "er le nom du dénonciateur et le prier",
    "jalons": [
      0,
      37
    ]
  },
  "entite_119": {
    "label": "LOC",
    "text": "Mathieu",
    "jalons": [
      197,
      204
    ]
  },
  "entite_120": {
    "label": "LOC",
    "text": "Corday",
    "jalons": [
      269,
      275
    ]
  },
  "entite_121": {
    "label": "LOC",
    "text": "Bientôt la nouvelle de la",
    "jalons": [
      482,
      507
    ]
  },
  "entite_122": {
    "label": "LOC",
    "text": "Ain",
    "jalons": [
      509,
      512
    ]
  },
  "entite_123": {
    "label": "MISC",
    "text": "Le président au nom de la société, lui donna le « nom de Marat",
    "jalons": [
      294,
      356
    ]
  },
  "entite_124": {
    "label": "LOC",
    "text": "Quelques",
    "jalons": [
      31,
      39
    ]
  },
  "entite_125": {
    "label": "MISC",
    "text": "Compiègne le nom « de Marat-sur-Oise",
    "jalons": [
      179,
      215
    ]
  },
  "entite_126": {
    "label": "MISC",
    "text": "Commune de Marat-sur-Oise",
    "jalons": [
      398,
      423
    ]
  },
  "entite_127": {
    "label": "MISC",
    "text": "la Convention « le vœu de la société",
    "jalons": [
      52,
      88
    ]
  },
  "entite_128": {
    "label": "MISC",
    "text": "nneur de Marat et dont la",
    "jalons": [
      0,
      25
    ]
  },
  "entite_129": {
    "label": "LOC",
    "text": "L'en deuxième de la République",
    "jalons": [
      336,
      366
    ]
  },
  "entite_130": {
    "label": "MISC",
    "text": "Buste de Rousseau porté par deux frères de la société",
    "jalons": [
      250,
      303
    ]
  },
  "entite_131": {
    "label": "LOC",
    "text": "flambeau de la Raison",
    "jalons": [
      292,
      313
    ]
  },
  "entite_132": {
    "label": "MISC",
    "text": "l’Ami du Peuple nous laisse",
    "jalons": [
      357,
      384
    ]
  },
  "entite_133": {
    "label": "MISC",
    "text": "Groupe de frères d'armes",
    "jalons": [
      115,
      139
    ]
  },
  "entite_134": {
    "label": "LOC",
    "text": "la rue de la Fédération",
    "jalons": [
      157,
      180
    ]
  },
  "entite_135": {
    "label": "LOC",
    "text": "le temple de la Liberté",
    "jalons": [
      201,
      224
    ]
  },
  "entite_136": {
    "label": "LOC",
    "text": "Saint-Jacques",
    "jalons": [
      236,
      249
    ]
  },
  "entite_137": {
    "label": "PER",
    "text": "Aujourd’hui rue d'Orléans",
    "jalons": [
      216,
      241
    ]
  },
  "entite_138": {
    "label": "LOC",
    "text": "Place de l'Hôtel de Ville",
    "jalons": [
      246,
      271
    ]
  },
  "entite_139": {
    "label": "LOC",
    "text": "celles de la Ré",
    "jalons": [
      294,
      309
    ]
  },
  "entite_140": {
    "label": "MISC",
    "text": "ceux de la Raison, de la Liberté et de l'Égalité",
    "jalons": [
      344,
      392
    ]
  },
  "entite_141": {
    "label": "MISC",
    "text": "la Liberté et en l’honneur de Pelletier et de Marat",
    "jalons": [
      99,
      150
    ]
  },
  "entite_142": {
    "label": "MISC",
    "text": "Dans la salle",
    "jalons": [
      421,
      434
    ]
  },
  "entite_143": {
    "label": "LOC",
    "text": "de la Raison",
    "jalons": [
      267,
      279
    ]
  },
  "entite_144": {
    "label": "PER",
    "text": "Eglise Saint-Antoine",
    "jalons": [
      224,
      244
    ]
  },
  "entite_145": {
    "label": "MISC",
    "text": "Ainour sacré de la Partie a",
    "jalons": [
      374,
      401
    ]
  },
  "entite_146": {
    "label": "PER",
    "text": "M. de Pron",
    "jalons": [
      258,
      268
    ]
  },
  "entite_147": {
    "label": "LOC",
    "text": "Bienfaisant",
    "jalons": [
      408,
      419
    ]
  },
  "entite_148": {
    "label": "LOC",
    "text": "Daignez",
    "jalons": [
      70,
      77
    ]
  },
  "entite_149": {
    "label": "LOC",
    "text": "Vatout",
    "jalons": [
      356,
      362
    ]
  },
  "entite_150": {
    "label": "LOC",
    "text": "Chéteau de Compiègne",
    "jalons": [
      367,
      387
    ]
  }
}