{
  "voc_eval_res": {
    "precision": 31.6327,
    "recall": 11.2727,
    "f-score": 16.622
  },
  "KL_res": {
    "KL divergence": 3.825657816460201,
    "Euclidean Dist.": 0.22086367833086112,
    "WER": 0.9404517453798767,
    "CER": 0.7445633413876424,
    "Cosine Dist.": 0.6378578513642221
  },
  "occ_eval_res": {
    "precision": 31.5789,
    "recall": 11.0883,
    "f-score": 16.4134
  },
  "clean_eval": {
    "f-score": 4.276315789473684,
    "precision": 2.8761061946902653,
    "recall": 8.333333333333332,
    "tp": 13,
    "fp": 439,
    "fn": 143
  },
  "jaccard": [
    0.7873303167420814
  ],
  "braycurtis": [
    0.6247464503042597
  ],
  "dice": [
    0.6492537313432836
  ],
  "cosinus": [
    0.321656573223274
  ]
}