{
  "voc_eval_res": {
    "precision": 66.0099,
    "recall": 31.1628,
    "f-score": 42.3381
  },
  "KL_res": {
    "KL divergence": 1.2789068427857677,
    "Euclidean Dist.": 0.11159894908076928,
    "WER": 0.7026209677419355,
    "CER": 0.5176805310933478,
    "Cosine Dist.": 0.07271317879601957
  },
  "occ_eval_res": {
    "precision": 68.608,
    "recall": 48.6895,
    "f-score": 56.9575
  },
  "clean_eval": {
    "f-score": 31.488801054018445,
    "precision": 27.47126436781609,
    "recall": 36.882716049382715,
    "tp": 239,
    "fp": 631,
    "fn": 409
  },
  "jaccard": [
    0.5391628677994198
  ],
  "braycurtis": [
    0.22169705154175107
  ],
  "dice": [
    0.3690780141843972
  ],
  "cosinus": [
    0.03568718709005314
  ]
}