{
  "voc_eval_res": {
    "precision": 38.7931,
    "recall": 35.7143,
    "f-score": 37.1901
  },
  "KL_res": {
    "KL divergence": 0.9665674129579098,
    "Euclidean Dist.": 0.06777312397407032,
    "WER": 0.6294117647058823,
    "CER": 0.5570621468926553,
    "Cosine Dist.": 0.008651638916288507
  },
  "occ_eval_res": {
    "precision": 69.883,
    "recall": 70.2941,
    "f-score": 70.088
  },
  "clean_eval": {
    "f-score": 14.264036418816389,
    "precision": 14.329268292682926,
    "recall": 14.19939577039275,
    "tp": 47,
    "fp": 281,
    "fn": 284
  },
  "jaccard": [
    0.5028712059064807
  ],
  "braycurtis": [
    0.1703276247207744
  ],
  "dice": [
    0.3358904109589041
  ],
  "cosinus": [
    0.013254239349353325
  ]
}