{
  "voc_eval_res": {
    "precision": 52.9517,
    "recall": 38.342,
    "f-score": 44.4778
  },
  "KL_res": {
    "KL divergence": 1.3282733385967094,
    "Euclidean Dist.": 0.0691899343804629,
    "WER": 0.6802368615840119,
    "CER": 0.4332148738840253,
    "Cosine Dist.": 0.09390447174853322
  },
  "occ_eval_res": {
    "precision": 54.0541,
    "recall": 50.3331,
    "f-score": 52.1273
  },
  "clean_eval": {
    "f-score": 42.5974025974026,
    "precision": 41.37931034482759,
    "recall": 43.889384478144514,
    "tp": 492,
    "fp": 697,
    "fn": 629
  },
  "jaccard": [
    0.4274929223026109
  ],
  "braycurtis": [
    0.1618574514038877
  ],
  "dice": [
    0.27185437087417486
  ],
  "cosinus": [
    0.026923451304171175
  ]
}