{
  "entite_0": {
    "label": "PER",
    "text": "Gallica",
    "jalons": [
      6,
      13
    ]
  },
  "entite_1": {
    "label": "LOC",
    "text": "département de l'Oise",
    "jalons": [
      18,
      39
    ]
  },
  "entite_2": {
    "label": "LOC",
    "text": "Compiègne",
    "jalons": [
      42,
      51
    ]
  },
  "entite_3": {
    "label": "PER",
    "text": "M rat",
    "jalons": [
      55,
      60
    ]
  },
  "entite_4": {
    "label": "PER",
    "text": "M.",
    "jalons": [
      89,
      91
    ]
  },
  "entite_5": {
    "label": "PER",
    "text": "Alexandre Sorel",
    "jalons": [
      93,
      108
    ]
  },
  "entite_6": {
    "label": "MISC",
    "text": "Bibliothèques de la Ville de Compiègne",
    "jalons": [
      137,
      175
    ]
  },
  "entite_7": {
    "label": "LOC",
    "text": "Compiègne",
    "jalons": [
      205,
      214
    ]
  },
  "entite_8": {
    "label": "PER",
    "text": "Marat",
    "jalons": [
      218,
      223
    ]
  },
  "entite_9": {
    "label": "PER",
    "text": "M.",
    "jalons": [
      251,
      253
    ]
  },
  "entite_10": {
    "label": "PER",
    "text": "Sorel",
    "jalons": [
      257,
      262
    ]
  },
  "entite_11": {
    "label": "PER",
    "text": "Alexandre",
    "jalons": [
      264,
      273
    ]
  },
  "entite_12": {
    "label": "PER",
    "text": "Alexandre Sorel",
    "jalons": [
      319,
      334
    ]
  },
  "entite_13": {
    "label": "MISC",
    "text": "Gallica",
    "jalons": [
      387,
      394
    ]
  },
  "entite_14": {
    "label": "MISC",
    "text": "BnF. Leur réutilisation",
    "jalons": [
      518,
      541
    ]
  },
  "entite_15": {
    "label": "ORG",
    "text": "Bibliothèque nationale de France",
    "jalons": [
      906,
      938
    ]
  },
  "entite_16": {
    "label": "ORG",
    "text": "BnF",
    "jalons": [
      970,
      973
    ]
  },
  "entite_17": {
    "label": "MISC",
    "text": "CLIQUER ICI",
    "jalons": [
      1471,
      1482
    ]
  },
  "entite_18": {
    "label": "ORG",
    "text": "ACCÉDER",
    "jalons": [
      1488,
      1495
    ]
  },
  "entite_19": {
    "label": "MISC",
    "text": "TARIFS",
    "jalons": [
      1500,
      1506
    ]
  },
  "entite_20": {
    "label": "MISC",
    "text": "À LA LICENCE\n\n",
    "jalons": [
      1510,
      1524
    ]
  },
  "entite_21": {
    "label": "LOC",
    "text": "Gallica",
    "jalons": [
      1543,
      1550
    ]
  },
  "entite_22": {
    "label": "ORG",
    "text": "BnF",
    "jalons": [
      1575,
      1578
    ]
  },
  "entite_23": {
    "label": "ORG",
    "text": "L.2112-1",
    "jalons": [
      1600,
      1608
    ]
  },
  "entite_24": {
    "label": "ORG",
    "text": "Source gallica.BnF.fr / Bibliothèque municipale de …",
    "jalons": [
      2119,
      2171
    ]
  },
  "entite_25": {
    "label": "LOC",
    "text": "Gallica",
    "jalons": [
      2303,
      2310
    ]
  },
  "entite_26": {
    "label": "ORG",
    "text": "BnF",
    "jalons": [
      2350,
      2353
    ]
  },
  "entite_27": {
    "label": "MISC",
    "text": "L341-1",
    "jalons": [
      2403,
      2409
    ]
  },
  "entite_28": {
    "label": "LOC",
    "text": "Gallica",
    "jalons": [
      2521,
      2528
    ]
  },
  "entite_29": {
    "label": "LOC",
    "text": "Gallica",
    "jalons": [
      3032,
      3039
    ]
  },
  "entite_30": {
    "label": "ORG",
    "text": "COMPAGNIE",
    "jalons": [
      3146,
      3155
    ]
  },
  "entite_31": {
    "label": "PER",
    "text": "M. ALEXANDRE SOREL",
    "jalons": [
      3196,
      3214
    ]
  },
  "entite_32": {
    "label": "MISC",
    "text": "AVocat",
    "jalons": [
      3217,
      3223
    ]
  },
  "entite_33": {
    "label": "LOC",
    "text": "Cour impériale de ‘Paris",
    "jalons": [
      3229,
      3253
    ]
  },
  "entite_34": {
    "label": "LOC",
    "text": "Loue",
    "jalons": [
      3258,
      3262
    ]
  },
  "entite_35": {
    "label": "ORG",
    "text": "EEE",
    "jalons": [
      3275,
      3278
    ]
  },
  "entite_36": {
    "label": "PER",
    "text": "Dot de te Ses",
    "jalons": [
      3285,
      3298
    ]
  },
  "entite_37": {
    "label": "LOC",
    "text": "Vo",
    "jalons": [
      3345,
      3347
    ]
  },
  "entite_38": {
    "label": "LOC",
    "text": "URI\n\nLit BEAUVAIS",
    "jalons": [
      3354,
      3371
    ]
  },
  "entite_39": {
    "label": "ORG",
    "text": "LIBRAIRE",
    "jalons": [
      3389,
      3397
    ]
  },
  "entite_40": {
    "label": "LOC",
    "text": "SAINT-SAUVEUR",
    "jalons": [
      3407,
      3420
    ]
  },
  "entite_41": {
    "label": "PER",
    "text": "Ste D",
    "jalons": [
      3466,
      3471
    ]
  },
  "entite_42": {
    "label": "ORG",
    "text": "IL A",
    "jalons": [
      3482,
      3486
    ]
  },
  "entite_43": {
    "label": "MISC",
    "text": "A D CR Que mes me nat",
    "jalons": [
      3517,
      3538
    ]
  },
  "entite_44": {
    "label": "ORG",
    "text": "TT",
    "jalons": [
      3545,
      3547
    ]
  },
  "entite_45": {
    "label": "ORG",
    "text": "IMPRIMERIE ROUSSEAU-LEROY",
    "jalons": [
      3567,
      3592
    ]
  },
  "entite_46": {
    "label": "ORG",
    "text": "nee",
    "jalons": [
      3613,
      3616
    ]
  },
  "entite_47": {
    "label": "PER",
    "text": "SAM",
    "jalons": [
      3641,
      3644
    ]
  },
  "entite_48": {
    "label": "ORG",
    "text": "DÉPARTEMENT DE",
    "jalons": [
      3667,
      3681
    ]
  },
  "entite_49": {
    "label": "ORG",
    "text": "COMPIÈGNE",
    "jalons": [
      3718,
      3727
    ]
  },
  "entite_50": {
    "label": "MISC",
    "text": "MARAT",
    "jalons": [
      3731,
      3736
    ]
  },
  "entite_51": {
    "label": "LOC",
    "text": "Paris",
    "jalons": [
      3805,
      3810
    ]
  },
  "entite_52": {
    "label": "ORG",
    "text": "Amis de la Constitution",
    "jalons": [
      3865,
      3888
    ]
  },
  "entite_53": {
    "label": "ORG",
    "text": "Société des Jacobins",
    "jalons": [
      3920,
      3940
    ]
  },
  "entite_54": {
    "label": "LOC",
    "text": "la France",
    "jalons": [
      4049,
      4058
    ]
  },
  "entite_55": {
    "label": "LOC",
    "text": "Beauvais",
    "jalons": [
      4345,
      4353
    ]
  },
  "entite_56": {
    "label": "LOC",
    "text": "département de l'Oise",
    "jalons": [
      4394,
      4415
    ]
  },
  "entite_57": {
    "label": "LOC",
    "text": "Moniteur",
    "jalons": [
      4481,
      4489
    ]
  },
  "entite_58": {
    "label": "LOC",
    "text": "Compiègne",
    "jalons": [
      4505,
      4514
    ]
  },
  "entite_59": {
    "label": "LOC",
    "text": "Compiègne",
    "jalons": [
      4592,
      4601
    ]
  },
  "entite_60": {
    "label": "ORG",
    "text": "Amis de la Constitution",
    "jalons": [
      4704,
      4727
    ]
  },
  "entite_61": {
    "label": "MISC",
    "text": "Amis de la\n«",
    "jalons": [
      4870,
      4882
    ]
  },
  "entite_62": {
    "label": "ORG",
    "text": "Constitution",
    "jalons": [
      4883,
      4895
    ]
  },
  "entite_63": {
    "label": "MISC",
    "text": "Contribution",
    "jalons": [
      5145,
      5157
    ]
  },
  "entite_64": {
    "label": "ORG",
    "text": "Société des Amis de la Constitution de Compiègne",
    "jalons": [
      5322,
      5370
    ]
  },
  "entite_65": {
    "label": "PER",
    "text": "jusqu’",
    "jalons": [
      5393,
      5399
    ]
  },
  "entite_66": {
    "label": "LOC",
    "text": "département de l'Oise",
    "jalons": [
      5562,
      5583
    ]
  },
  "entite_67": {
    "label": "PER",
    "text": "m’",
    "jalons": [
      5588,
      5590
    ]
  },
  "entite_68": {
    "label": "LOC",
    "text": "Compiègne",
    "jalons": [
      5800,
      5809
    ]
  },
  "entite_69": {
    "label": "LOC",
    "text": "p. 554",
    "jalons": [
      5849,
      5855
    ]
  },
  "entite_70": {
    "label": "LOC",
    "text": "Id",
    "jalons": [
      5861,
      5863
    ]
  },
  "entite_71": {
    "label": "MISC",
    "text": "VIII",
    "jalons": [
      5869,
      5873
    ]
  },
  "entite_72": {
    "label": "PER",
    "text": "Tribale",
    "jalons": [
      5932,
      5939
    ]
  },
  "entite_73": {
    "label": "PER",
    "text": "Stanislas Leféron",
    "jalons": [
      6071,
      6088
    ]
  },
  "entite_74": {
    "label": "ORG",
    "text": "Société des Amis de la Constitution",
    "jalons": [
      6166,
      6201
    ]
  },
  "entite_75": {
    "label": "PER",
    "text": "Roi",
    "jalons": [
      6282,
      6285
    ]
  },
  "entite_76": {
    "label": "ORG",
    "text": "l’Assemblée",
    "jalons": [
      6362,
      6373
    ]
  },
  "entite_77": {
    "label": "PER",
    "text": "Roi",
    "jalons": [
      6405,
      6408
    ]
  },
  "entite_78": {
    "label": "LOC",
    "text": "St-Jacques",
    "jalons": [
      6501,
      6511
    ]
  },
  "entite_79": {
    "label": "PER",
    "text": "Mirabeau",
    "jalons": [
      6560,
      6568
    ]
  },
  "entite_80": {
    "label": "MISC",
    "text": "Constitution de Noyon",
    "jalons": [
      6808,
      6829
    ]
  },
  "entite_81": {
    "label": "PER",
    "text": "s’",
    "jalons": [
      6860,
      6862
    ]
  },
  "entite_82": {
    "label": "LOC",
    "text": "Compiègne",
    "jalons": [
      6882,
      6891
    ]
  },
  "entite_83": {
    "label": "PER",
    "text": "Messieurs",
    "jalons": [
      6962,
      6971
    ]
  },
  "entite_84": {
    "label": "LOC",
    "text": "Noyon",
    "jalons": [
      6975,
      6980
    ]
  },
  "entite_85": {
    "label": "PER",
    "text": "d’",
    "jalons": [
      7024,
      7026
    ]
  },
  "entite_86": {
    "label": "ORG",
    "text": "bull",
    "jalons": [
      7163,
      7167
    ]
  },
  "entite_87": {
    "label": "PER",
    "text": "n’",
    "jalons": [
      7194,
      7196
    ]
  },
  "entite_88": {
    "label": "ORG",
    "text": "Constitution",
    "jalons": [
      7373,
      7385
    ]
  },
  "entite_89": {
    "label": "ORG",
    "text": "Constitution",
    "jalons": [
      7758,
      7770
    ]
  },
  "entite_90": {
    "label": "LOC",
    "text": "Venait",
    "jalons": [
      8012,
      8018
    ]
  },
  "entite_91": {
    "label": "LOC",
    "text": "l’",
    "jalons": [
      8027,
      8029
    ]
  },
  "entite_92": {
    "label": "ORG",
    "text": "POPULI SUPREMA LEX",
    "jalons": [
      8277,
      8295
    ]
  },
  "entite_93": {
    "label": "ORG",
    "text": "Constitution",
    "jalons": [
      8366,
      8378
    ]
  },
  "entite_94": {
    "label": "LOC",
    "text": "A",
    "jalons": [
      8404,
      8405
    ]
  },
  "entite_95": {
    "label": "LOC",
    "text": "FR À & A",
    "jalons": [
      8410,
      8418
    ]
  },
  "entite_96": {
    "label": "MISC",
    "text": "Æ",
    "jalons": [
      8429,
      8430
    ]
  },
  "entite_97": {
    "label": "PER",
    "text": "s’",
    "jalons": [
      8582,
      8584
    ]
  },
  "entite_98": {
    "label": "ORG",
    "text": "s’",
    "jalons": [
      8731,
      8733
    ]
  },
  "entite_99": {
    "label": "ORG",
    "text": "Jda-",
    "jalons": [
      8757,
      8761
    ]
  },
  "entite_100": {
    "label": "LOC",
    "text": "Paris",
    "jalons": [
      8771,
      8776
    ]
  },
  "entite_101": {
    "label": "LOC",
    "text": "Beauvais",
    "jalons": [
      8791,
      8799
    ]
  },
  "entite_102": {
    "label": "PER",
    "text": "M. Massieu",
    "jalons": [
      8855,
      8865
    ]
  },
  "entite_103": {
    "label": "LOC",
    "text": "département de l'Oise",
    "jalons": [
      8877,
      8898
    ]
  },
  "entite_104": {
    "label": "PER",
    "text": "Renard",
    "jalons": [
      9012,
      9018
    ]
  },
  "entite_105": {
    "label": "PER",
    "text": "M. Massieu",
    "jalons": [
      9076,
      9086
    ]
  },
  "entite_106": {
    "label": "MISC",
    "text": "Constitution de Noyon",
    "jalons": [
      9159,
      9180
    ]
  },
  "entite_107": {
    "label": "LOC",
    "text": "Compiègne",
    "jalons": [
      9230,
      9239
    ]
  },
  "entite_108": {
    "label": "MISC",
    "text": "Jacobins de Paris",
    "jalons": [
      9281,
      9298
    ]
  },
  "entite_109": {
    "label": "PER",
    "text": "s’",
    "jalons": [
      9360,
      9362
    ]
  },
  "entite_110": {
    "label": "PER",
    "text": "Massieu",
    "jalons": [
      9449,
      9456
    ]
  },
  "entite_111": {
    "label": "LOC",
    "text": "Beauvais",
    "jalons": [
      9524,
      9532
    ]
  },
  "entite_112": {
    "label": "LOC",
    "text": "l’",
    "jalons": [
      9537,
      9539
    ]
  },
  "entite_113": {
    "label": "LOC",
    "text": "l’",
    "jalons": [
      9580,
      9582
    ]
  },
  "entite_114": {
    "label": "LOC",
    "text": "Jean-Jacques-Rousseau",
    "jalons": [
      9697,
      9718
    ]
  },
  "entite_115": {
    "label": "PER",
    "text": "race-",
    "jalons": [
      9957,
      9962
    ]
  },
  "entite_116": {
    "label": "PER",
    "text": "Massieu",
    "jalons": [
      9981,
      9988
    ]
  },
  "entite_117": {
    "label": "LOC",
    "text": "Rainville",
    "jalons": [
      10046,
      10055
    ]
  },
  "entite_118": {
    "label": "LOC",
    "text": "Noyon",
    "jalons": [
      10071,
      10076
    ]
  },
  "entite_119": {
    "label": "PER",
    "text": "Gibert",
    "jalons": [
      10078,
      10084
    ]
  },
  "entite_120": {
    "label": "PER",
    "text": "Penon",
    "jalons": [
      10140,
      10145
    ]
  },
  "entite_121": {
    "label": "PER",
    "text": "Massieu",
    "jalons": [
      10303,
      10310
    ]
  },
  "entite_122": {
    "label": "PER",
    "text": "Jean-Baptiste",
    "jalons": [
      10312,
      10325
    ]
  },
  "entite_123": {
    "label": "PER",
    "text": "Serge",
    "jalons": [
      10341,
      10346
    ]
  },
  "entite_124": {
    "label": "LOC",
    "text": "Senlis",
    "jalons": [
      10392,
      10398
    ]
  },
  "entite_125": {
    "label": "LOC",
    "text": "États-Généraux",
    "jalons": [
      10411,
      10425
    ]
  },
  "entite_126": {
    "label": "LOC",
    "text": "département de l'Oise",
    "jalons": [
      10488,
      10509
    ]
  },
  "entite_127": {
    "label": "MISC",
    "text": "Convention",
    "jalons": [
      10535,
      10545
    ]
  },
  "entite_128": {
    "label": "PER",
    "text": "Louis XVI",
    "jalons": [
      10566,
      10575
    ]
  },
  "entite_129": {
    "label": "PER",
    "text": "Jai",
    "jalons": [
      10595,
      10598
    ]
  },
  "entite_130": {
    "label": "ORG",
    "text": "l’",
    "jalons": [
      10896,
      10898
    ]
  },
  "entite_131": {
    "label": "PER",
    "text": "Massieu",
    "jalons": [
      10944,
      10951
    ]
  },
  "entite_132": {
    "label": "LOC",
    "text": "Givet",
    "jalons": [
      11017,
      11022
    ]
  },
  "entite_133": {
    "label": "LOC",
    "text": "Bruxelles",
    "jalons": [
      11036,
      11045
    ]
  },
  "entite_134": {
    "label": "LOC",
    "text": "l’",
    "jalons": [
      11187,
      11189
    ]
  },
  "entite_135": {
    "label": "LOC",
    "text": "district de Compiègne",
    "jalons": [
      11407,
      11428
    ]
  },
  "entite_136": {
    "label": "LOC",
    "text": "Noyon",
    "jalons": [
      11624,
      11629
    ]
  },
  "entite_137": {
    "label": "PER",
    "text": "qu’",
    "jalons": [
      11755,
      11758
    ]
  },
  "entite_138": {
    "label": "PER",
    "text": "M. Massieu",
    "jalons": [
      11772,
      11782
    ]
  },
  "entite_139": {
    "label": "LOC",
    "text": "Compiègne",
    "jalons": [
      11902,
      11911
    ]
  },
  "entite_140": {
    "label": "LOC",
    "text": "Noyon",
    "jalons": [
      12019,
      12024
    ]
  },
  "entite_141": {
    "label": "ORG",
    "text": "l’",
    "jalons": [
      12050,
      12052
    ]
  },
  "entite_142": {
    "label": "PER",
    "text": "M. Massieu",
    "jalons": [
      12246,
      12256
    ]
  },
  "entite_143": {
    "label": "PER",
    "text": "M. Massieu",
    "jalons": [
      12340,
      12350
    ]
  },
  "entite_144": {
    "label": "PER",
    "text": "M. Libert",
    "jalons": [
      12354,
      12363
    ]
  },
  "entite_145": {
    "label": "LOC",
    "text": "Compiègne",
    "jalons": [
      12436,
      12445
    ]
  },
  "entite_146": {
    "label": "LOC",
    "text": "loix",
    "jalons": [
      12668,
      12672
    ]
  },
  "entite_147": {
    "label": "PER",
    "text": "M. Louis-Joseph-Stanislas Leféron",
    "jalons": [
      12697,
      12730
    ]
  },
  "entite_148": {
    "label": "LOC",
    "text": "L’",
    "jalons": [
      12892,
      12894
    ]
  },
  "entite_149": {
    "label": "PER",
    "text": "M. Leféron",
    "jalons": [
      12911,
      12921
    ]
  },
  "entite_150": {
    "label": "PER",
    "text": "Bertrand",
    "jalons": [
      12962,
      12970
    ]
  },
  "entite_151": {
    "label": "PER",
    "text": "M. Chabanon",
    "jalons": [
      12987,
      12998
    ]
  },
  "entite_152": {
    "label": "ORG",
    "text": "l’Académie\nFrançaise",
    "jalons": [
      13021,
      13041
    ]
  },
  "entite_153": {
    "label": "LOC",
    "text": "A",
    "jalons": [
      13044,
      13045
    ]
  },
  "entite_154": {
    "label": "LOC",
    "text": "l’",
    "jalons": [
      13105,
      13107
    ]
  },
  "entite_155": {
    "label": "LOC",
    "text": "St-Jacques",
    "jalons": [
      13119,
      13129
    ]
  },
  "entite_156": {
    "label": "ORG",
    "text": "Corps Administratifs",
    "jalons": [
      13205,
      13225
    ]
  },
  "entite_157": {
    "label": "MISC",
    "text": "Militaires de vouloir bien",
    "jalons": [
      13229,
      13255
    ]
  },
  "entite_158": {
    "label": "PER",
    "text": "s’",
    "jalons": [
      13256,
      13258
    ]
  },
  "entite_159": {
    "label": "LOC",
    "text": "Conseil général de Compiègne",
    "jalons": [
      13572,
      13600
    ]
  },
  "entite_160": {
    "label": "ORG",
    "text": "Conseil",
    "jalons": [
      13675,
      13682
    ]
  },
  "entite_161": {
    "label": "LOC",
    "text": "AR",
    "jalons": [
      13703,
      13705
    ]
  },
  "entite_162": {
    "label": "LOC",
    "text": "B",
    "jalons": [
      13716,
      13717
    ]
  },
  "entite_163": {
    "label": "ORG",
    "text": "l’Assemblée nationale",
    "jalons": [
      13763,
      13784
    ]
  },
  "entite_164": {
    "label": "ORG",
    "text": "Constitution",
    "jalons": [
      14042,
      14054
    ]
  },
  "entite_165": {
    "label": "ORG",
    "text": "l’",
    "jalons": [
      14069,
      14071
    ]
  },
  "entite_166": {
    "label": "LOC",
    "text": "Paris",
    "jalons": [
      14287,
      14292
    ]
  },
  "entite_167": {
    "label": "PER",
    "text": "Le roi",
    "jalons": [
      14294,
      14300
    ]
  },
  "entite_168": {
    "label": "ORG",
    "text": "Constitution",
    "jalons": [
      14318,
      14330
    ]
  },
  "entite_169": {
    "label": "ORG",
    "text": "Com-",
    "jalons": [
      14376,
      14380
    ]
  },
  "entite_170": {
    "label": "MISC",
    "text": "lettre du Roï",
    "jalons": [
      14432,
      14445
    ]
  },
  "entite_171": {
    "label": "PER",
    "text": "Louis XVI",
    "jalons": [
      14636,
      14645
    ]
  },
  "entite_172": {
    "label": "MISC",
    "text": "Amis de la Constitution de Compiègne",
    "jalons": [
      14854,
      14890
    ]
  },
  "entite_173": {
    "label": "PER",
    "text": "s’asso -",
    "jalons": [
      15194,
      15202
    ]
  },
  "entite_174": {
    "label": "MISC",
    "text": "MM. Thibaut",
    "jalons": [
      15215,
      15226
    ]
  },
  "entite_175": {
    "label": "LOC",
    "text": "Berger",
    "jalons": [
      15228,
      15234
    ]
  },
  "entite_176": {
    "label": "LOC",
    "text": "Saiget",
    "jalons": [
      15236,
      15242
    ]
  },
  "entite_177": {
    "label": "LOC",
    "text": "Chauffour",
    "jalons": [
      15244,
      15253
    ]
  },
  "entite_178": {
    "label": "PER",
    "text": "Wattelet",
    "jalons": [
      15255,
      15263
    ]
  },
  "entite_179": {
    "label": "PER",
    "text": "Mercier",
    "jalons": [
      15265,
      15272
    ]
  },
  "entite_180": {
    "label": "LOC",
    "text": "Courtois",
    "jalons": [
      15274,
      15282
    ]
  },
  "entite_181": {
    "label": "LOC",
    "text": "Lambin",
    "jalons": [
      15284,
      15290
    ]
  },
  "entite_182": {
    "label": "LOC",
    "text": "Veron",
    "jalons": [
      15292,
      15297
    ]
  },
  "entite_183": {
    "label": "LOC",
    "text": "Rey",
    "jalons": [
      15299,
      15302
    ]
  },
  "entite_184": {
    "label": "LOC",
    "text": "Beaugrand",
    "jalons": [
      15304,
      15313
    ]
  },
  "entite_185": {
    "label": "LOC",
    "text": "Chambon",
    "jalons": [
      15315,
      15322
    ]
  },
  "entite_186": {
    "label": "LOC",
    "text": "Monies",
    "jalons": [
      15326,
      15332
    ]
  },
  "entite_187": {
    "label": "ORG",
    "text": "Conseil",
    "jalons": [
      15395,
      15402
    ]
  },
  "entite_188": {
    "label": "ORG",
    "text": "MM.",
    "jalons": [
      15418,
      15421
    ]
  },
  "entite_189": {
    "label": "ORG",
    "text": "Auger",
    "jalons": [
      15424,
      15429
    ]
  },
  "entite_190": {
    "label": "ORG",
    "text": "Thi-",
    "jalons": [
      15431,
      15435
    ]
  },
  "entite_191": {
    "label": "PER",
    "text": "Étienne Poulain",
    "jalons": [
      15444,
      15459
    ]
  },
  "entite_192": {
    "label": "ORG",
    "text": "Société des Amis de\nla Constitution",
    "jalons": [
      15488,
      15523
    ]
  },
  "entite_193": {
    "label": "PER",
    "text": "Leséron",
    "jalons": [
      15614,
      15621
    ]
  },
  "entite_194": {
    "label": "LOC",
    "text": "Con-",
    "jalons": [
      15709,
      15713
    ]
  },
  "entite_195": {
    "label": "PER",
    "text": "M.",
    "jalons": [
      15784,
      15786
    ]
  },
  "entite_196": {
    "label": "PER",
    "text": "Leséron",
    "jalons": [
      16064,
      16071
    ]
  },
  "entite_197": {
    "label": "MISC",
    "text": "d’",
    "jalons": [
      16119,
      16121
    ]
  },
  "entite_198": {
    "label": "ORG",
    "text": "nee",
    "jalons": [
      16234,
      16237
    ]
  },
  "entite_199": {
    "label": "LOC",
    "text": "Lomme",
    "jalons": [
      16248,
      16253
    ]
  },
  "entite_200": {
    "label": "PER",
    "text": "n’",
    "jalons": [
      16380,
      16382
    ]
  },
  "entite_201": {
    "label": "LOC",
    "text": "Arrêle",
    "jalons": [
      16749,
      16755
    ]
  },
  "entite_202": {
    "label": "MISC",
    "text": "an IV",
    "jalons": [
      16800,
      16805
    ]
  },
  "entite_203": {
    "label": "LOC",
    "text": "Li-",
    "jalons": [
      16813,
      16816
    ]
  },
  "entite_204": {
    "label": "MISC",
    "text": "qu’on reformât",
    "jalons": [
      17225,
      17239
    ]
  },
  "entite_205": {
    "label": "ORG",
    "text": "Amis de la République",
    "jalons": [
      17309,
      17330
    ]
  },
  "entite_206": {
    "label": "ORG",
    "text": "Amis de la\nConstitution fat",
    "jalons": [
      17393,
      17420
    ]
  },
  "entite_207": {
    "label": "LOC",
    "text": "l’",
    "jalons": [
      17433,
      17435
    ]
  },
  "entite_208": {
    "label": "ORG",
    "text": "Amis de la République",
    "jalons": [
      17453,
      17474
    ]
  },
  "entite_209": {
    "label": "MISC",
    "text": "l'Auditoire",
    "jalons": [
      17525,
      17536
    ]
  },
  "entite_210": {
    "label": "MISC",
    "text": "Les arrêtés",
    "jalons": [
      17661,
      17672
    ]
  },
  "entite_211": {
    "label": "LOC",
    "text": "Paris",
    "jalons": [
      17865,
      17870
    ]
  },
  "entite_212": {
    "label": "LOC",
    "text": "Tuileries",
    "jalons": [
      17920,
      17929
    ]
  },
  "entite_213": {
    "label": "ORG",
    "text": "l’",
    "jalons": [
      18080,
      18082
    ]
  },
  "entite_214": {
    "label": "PER",
    "text": "Décart",
    "jalons": [
      18222,
      18228
    ]
  },
  "entite_215": {
    "label": "PER",
    "text": "n’",
    "jalons": [
      18383,
      18385
    ]
  },
  "entite_216": {
    "label": "PER",
    "text": "Sainte- Marie",
    "jalons": [
      18475,
      18488
    ]
  },
  "entite_217": {
    "label": "LOC",
    "text": "l’",
    "jalons": [
      18513,
      18515
    ]
  },
  "entite_218": {
    "label": "LOC",
    "text": "abbaye de",
    "jalons": [
      18524,
      18533
    ]
  },
  "entite_219": {
    "label": "LOC",
    "text": "Saint-Corneille",
    "jalons": [
      18534,
      18549
    ]
  },
  "entite_220": {
    "label": "LOC",
    "text": "Compiègne",
    "jalons": [
      18606,
      18615
    ]
  },
  "entite_221": {
    "label": "ORG",
    "text": "Amis de la République",
    "jalons": [
      18640,
      18661
    ]
  },
  "entite_222": {
    "label": "LOC",
    "text": "Paris",
    "jalons": [
      18918,
      18923
    ]
  },
  "entite_223": {
    "label": "ORG",
    "text": "Jacobins",
    "jalons": [
      18934,
      18942
    ]
  },
  "entite_224": {
    "label": "MISC",
    "text": "Révolution",
    "jalons": [
      18989,
      18999
    ]
  },
  "entite_225": {
    "label": "LOC",
    "text": "la France",
    "jalons": [
      19021,
      19030
    ]
  },
  "entite_226": {
    "label": "PER",
    "text": "qu’",
    "jalons": [
      19083,
      19086
    ]
  },
  "entite_227": {
    "label": "LOC",
    "text": "Compiègne",
    "jalons": [
      19116,
      19125
    ]
  },
  "entite_228": {
    "label": "LOC",
    "text": "Marseillais",
    "jalons": [
      19341,
      19352
    ]
  },
  "entite_229": {
    "label": "LOC",
    "text": "Savoie",
    "jalons": [
      19589,
      19595
    ]
  },
  "entite_230": {
    "label": "MISC",
    "text": "Sarde",
    "jalons": [
      19621,
      19626
    ]
  },
  "entite_231": {
    "label": "MISC",
    "text": "d’",
    "jalons": [
      20087,
      20089
    ]
  },
  "entite_232": {
    "label": "MISC",
    "text": "c’",
    "jalons": [
      20199,
      20201
    ]
  },
  "entite_233": {
    "label": "LOC",
    "text": "Marseillais",
    "jalons": [
      20389,
      20400
    ]
  },
  "entite_234": {
    "label": "MISC",
    "text": "Qu'on\n_rayerait du procès-verbal",
    "jalons": [
      20415,
      20447
    ]
  },
  "entite_235": {
    "label": "PER",
    "text": "Montagnard",
    "jalons": [
      20469,
      20479
    ]
  },
  "entite_236": {
    "label": "MISC",
    "text": "Qu'on adresserait une\npétition au conseil municipal",
    "jalons": [
      20622,
      20673
    ]
  },
  "entite_237": {
    "label": "PER",
    "text": "Lambert de\nBallyhier",
    "jalons": [
      20922,
      20942
    ]
  },
  "entite_238": {
    "label": "MISC",
    "text": "Compiègne historique et monumentale",
    "jalons": [
      20970,
      21005
    ]
  },
  "entite_239": {
    "label": "LOC",
    "text": "p.279",
    "jalons": [
      21012,
      21017
    ]
  },
  "entite_240": {
    "label": "MISC",
    "text": "d’",
    "jalons": [
      21111,
      21113
    ]
  },
  "entite_241": {
    "label": "LOC",
    "text": "République",
    "jalons": [
      21422,
      21432
    ]
  },
  "entite_242": {
    "label": "PER",
    "text": "n’",
    "jalons": [
      21597,
      21599
    ]
  },
  "entite_243": {
    "label": "LOC",
    "text": "A",
    "jalons": [
      21965,
      21966
    ]
  },
  "entite_244": {
    "label": "LOC",
    "text": "Cambrai",
    "jalons": [
      22127,
      22134
    ]
  },
  "entite_245": {
    "label": "LOC",
    "text": "du Nord",
    "jalons": [
      22208,
      22215
    ]
  },
  "entite_246": {
    "label": "LOC",
    "text": "l’",
    "jalons": [
      22221,
      22223
    ]
  },
  "entite_247": {
    "label": "LOC",
    "text": "Valenciennes",
    "jalons": [
      22237,
      22249
    ]
  },
  "entite_248": {
    "label": "PER",
    "text": "t Quesnoy",
    "jalons": [
      22256,
      22265
    ]
  },
  "entite_249": {
    "label": "PER",
    "text": "qu’",
    "jalons": [
      22288,
      22291
    ]
  },
  "entite_250": {
    "label": "LOC",
    "text": "Marseillais",
    "jalons": [
      22492,
      22503
    ]
  },
  "entite_251": {
    "label": "LOC",
    "text": "I",
    "jalons": [
      22659,
      22660
    ]
  },
  "entite_252": {
    "label": "LOC",
    "text": "Compiègne",
    "jalons": [
      22744,
      22753
    ]
  },
  "entite_253": {
    "label": "MISC",
    "text": "Un membre leur jura",
    "jalons": [
      22904,
      22923
    ]
  },
  "entite_254": {
    "label": "LOC",
    "text": "Compiègne",
    "jalons": [
      22968,
      22977
    ]
  },
  "entite_255": {
    "label": "LOC",
    "text": "charlatan",
    "jalons": [
      23238,
      23247
    ]
  },
  "entite_256": {
    "label": "LOC",
    "text": "A",
    "jalons": [
      23595,
      23596
    ]
  },
  "entite_257": {
    "label": "MISC",
    "text": "CS",
    "jalons": [
      23607,
      23609
    ]
  },
  "entite_258": {
    "label": "LOC",
    "text": "A",
    "jalons": [
      23640,
      23641
    ]
  },
  "entite_259": {
    "label": "LOC",
    "text": "Republique",
    "jalons": [
      23745,
      23755
    ]
  },
  "entite_260": {
    "label": "PER",
    "text": "Vive",
    "jalons": [
      23820,
      23824
    ]
  },
  "entite_261": {
    "label": "PER",
    "text": "qu’",
    "jalons": [
      24016,
      24019
    ]
  },
  "entite_262": {
    "label": "MISC",
    "text": "qu’on mette",
    "jalons": [
      24388,
      24399
    ]
  },
  "entite_263": {
    "label": "LOC",
    "text": "l’",
    "jalons": [
      24520,
      24522
    ]
  },
  "entite_264": {
    "label": "MISC",
    "text": "citoyen CG",
    "jalons": [
      24635,
      24645
    ]
  },
  "entite_265": {
    "label": "LOC",
    "text": "s’",
    "jalons": [
      24677,
      24679
    ]
  },
  "entite_266": {
    "label": "PER",
    "text": "n’",
    "jalons": [
      24882,
      24884
    ]
  },
  "entite_267": {
    "label": "PER",
    "text": "Marat",
    "jalons": [
      24976,
      24981
    ]
  },
  "entite_268": {
    "label": "ORG",
    "text": "Amis de la République de Compiègne",
    "jalons": [
      25001,
      25035
    ]
  },
  "entite_269": {
    "label": "PER",
    "text": "Publiciste de la République française",
    "jalons": [
      25058,
      25095
    ]
  },
  "entite_270": {
    "label": "MISC",
    "text": "Ami du peuple",
    "jalons": [
      25120,
      25133
    ]
  },
  "entite_271": {
    "label": "ORG",
    "text": "UF",
    "jalons": [
      25159,
      25161
    ]
  },
  "entite_272": {
    "label": "PER",
    "text": "abel",
    "jalons": [
      25178,
      25182
    ]
  },
  "entite_273": {
    "label": "LOC",
    "text": "Compiègne",
    "jalons": [
      25264,
      25273
    ]
  },
  "entite_274": {
    "label": "LOC",
    "text": "République\nfrançaise",
    "jalons": [
      25310,
      25330
    ]
  },
  "entite_275": {
    "label": "MISC",
    "text": "CITOYEN",
    "jalons": [
      25336,
      25343
    ]
  },
  "entite_276": {
    "label": "ORG",
    "text": "MARAT",
    "jalons": [
      25344,
      25349
    ]
  },
  "entite_277": {
    "label": "MISC",
    "text": "c’",
    "jalons": [
      25375,
      25377
    ]
  },
  "entite_278": {
    "label": "LOC",
    "text": "République",
    "jalons": [
      25522,
      25532
    ]
  },
  "entite_279": {
    "label": "LOC",
    "text": "Moniteur",
    "jalons": [
      25566,
      25574
    ]
  },
  "entite_280": {
    "label": "LOC",
    "text": "l’",
    "jalons": [
      25578,
      25580
    ]
  },
  "entite_281": {
    "label": "MISC",
    "text": "Convention",
    "jalons": [
      25594,
      25604
    ]
  },
  "entite_282": {
    "label": "PER",
    "text": "général Vitgenkoff",
    "jalons": [
      25633,
      25651
    ]
  },
  "entite_283": {
    "label": "LOC",
    "text": "département de",
    "jalons": [
      25723,
      25737
    ]
  },
  "entite_284": {
    "label": "LOC",
    "text": "Mayenne",
    "jalons": [
      25738,
      25745
    ]
  },
  "entite_285": {
    "label": "LOC",
    "text": "Loire",
    "jalons": [
      25750,
      25755
    ]
  },
  "entite_286": {
    "label": "PER",
    "text": "Albite",
    "jalons": [
      25800,
      25806
    ]
  },
  "entite_287": {
    "label": "MISC",
    "text": "Convention",
    "jalons": [
      25863,
      25873
    ]
  },
  "entite_288": {
    "label": "PER",
    "text": "Vitgen",
    "jalons": [
      25888,
      25894
    ]
  },
  "entite_289": {
    "label": "MISC",
    "text": "Ce e\nNW",
    "jalons": [
      25904,
      25911
    ]
  },
  "entite_290": {
    "label": "MISC",
    "text": "En mm mme ms\n\f\n",
    "jalons": [
      25960,
      25975
    ]
  },
  "entite_291": {
    "label": "LOC",
    "text": "l’",
    "jalons": [
      26058,
      26060
    ]
  },
  "entite_292": {
    "label": "LOC",
    "text": "Compiègne",
    "jalons": [
      26229,
      26238
    ]
  },
  "entite_293": {
    "label": "LOC",
    "text": "Ourscamp",
    "jalons": [
      26274,
      26282
    ]
  },
  "entite_294": {
    "label": "LOC",
    "text": "Paris",
    "jalons": [
      26339,
      26344
    ]
  },
  "entite_295": {
    "label": "PER",
    "text": "général Vitgenkoff",
    "jalons": [
      26470,
      26488
    ]
  },
  "entite_296": {
    "label": "LOC",
    "text": "Tuileries",
    "jalons": [
      26524,
      26533
    ]
  },
  "entite_297": {
    "label": "ORG",
    "text": "l’Assemblée",
    "jalons": [
      26605,
      26616
    ]
  },
  "entite_298": {
    "label": "MISC",
    "text": "c’",
    "jalons": [
      26725,
      26727
    ]
  },
  "entite_299": {
    "label": "LOC",
    "text": "Marseillois",
    "jalons": [
      27083,
      27094
    ]
  },
  "entite_300": {
    "label": "ORG",
    "text": "l’Assemblée législative",
    "jalons": [
      27127,
      27150
    ]
  },
  "entite_301": {
    "label": "LOC",
    "text": "qu’",
    "jalons": [
      27152,
      27155
    ]
  },
  "entite_302": {
    "label": "PER",
    "text": "qu’",
    "jalons": [
      27249,
      27252
    ]
  },
  "entite_303": {
    "label": "MISC",
    "text": "c’",
    "jalons": [
      27302,
      27304
    ]
  },
  "entite_304": {
    "label": "MISC",
    "text": "Huit jours",
    "jalons": [
      27389,
      27399
    ]
  },
  "entite_305": {
    "label": "MISC",
    "text": "c’",
    "jalons": [
      27585,
      27587
    ]
  },
  "entite_306": {
    "label": "LOC",
    "text": "Compiègne",
    "jalons": [
      27622,
      27631
    ]
  },
  "entite_307": {
    "label": "LOC",
    "text": "l’",
    "jalons": [
      28012,
      28014
    ]
  },
  "entite_308": {
    "label": "PER",
    "text": "qu’",
    "jalons": [
      28146,
      28149
    ]
  },
  "entite_309": {
    "label": "LOC",
    "text": "Montagne",
    "jalons": [
      28392,
      28400
    ]
  },
  "entite_310": {
    "label": "LOC",
    "text": "Paris",
    "jalons": [
      28489,
      28494
    ]
  },
  "entite_311": {
    "label": "MISC",
    "text": "A\nRe",
    "jalons": [
      28550,
      28554
    ]
  },
  "entite_312": {
    "label": "ORG",
    "text": "SR",
    "jalons": [
      28556,
      28558
    ]
  },
  "entite_313": {
    "label": "LOC",
    "text": "B",
    "jalons": [
      28577,
      28578
    ]
  },
  "entite_314": {
    "label": "PER",
    "text": "Marat",
    "jalons": [
      28676,
      28681
    ]
  },
  "entite_315": {
    "label": "LOC",
    "text": "Prenez",
    "jalons": [
      28781,
      28787
    ]
  },
  "entite_316": {
    "label": "PER",
    "text": "Recevez",
    "jalons": [
      29018,
      29025
    ]
  },
  "entite_317": {
    "label": "MISC",
    "text": "Compiénoise",
    "jalons": [
      29142,
      29153
    ]
  },
  "entite_318": {
    "label": "LOC",
    "text": "Compiègne",
    "jalons": [
      29290,
      29299
    ]
  },
  "entite_319": {
    "label": "MISC",
    "text": "C",
    "jalons": [
      29459,
      29460
    ]
  },
  "entite_320": {
    "label": "PER",
    "text": "M",
    "jalons": [
      29467,
      29468
    ]
  },
  "entite_321": {
    "label": "LOC",
    "text": "Compiègne",
    "jalons": [
      29603,
      29612
    ]
  },
  "entite_322": {
    "label": "PER",
    "text": "Marat",
    "jalons": [
      29671,
      29676
    ]
  },
  "entite_323": {
    "label": "PER",
    "text": "Mathieu",
    "jalons": [
      29893,
      29900
    ]
  },
  "entite_324": {
    "label": "MISC",
    "text": "Convention",
    "jalons": [
      29915,
      29925
    ]
  },
  "entite_325": {
    "label": "PER",
    "text": "Marat",
    "jalons": [
      29958,
      29963
    ]
  },
  "entite_326": {
    "label": "LOC",
    "text": "Compiègne",
    "jalons": [
      29995,
      30004
    ]
  },
  "entite_327": {
    "label": "PER",
    "text": "Marat",
    "jalons": [
      30097,
      30102
    ]
  },
  "entite_328": {
    "label": "PER",
    "text": "s’",
    "jalons": [
      30126,
      30128
    ]
  },
  "entite_329": {
    "label": "MISC",
    "text": "c’",
    "jalons": [
      30203,
      30205
    ]
  },
  "entite_330": {
    "label": "MISC",
    "text": "Patriote Marat",
    "jalons": [
      30392,
      30406
    ]
  },
  "entite_331": {
    "label": "PER",
    "text": "Charlotte Corday",
    "jalons": [
      30467,
      30483
    ]
  },
  "entite_332": {
    "label": "PER",
    "text": "Marat",
    "jalons": [
      30724,
      30729
    ]
  },
  "entite_333": {
    "label": "LOC",
    "text": "Compiègne",
    "jalons": [
      30740,
      30749
    ]
  },
  "entite_334": {
    "label": "PER",
    "text": "s’",
    "jalons": [
      30766,
      30768
    ]
  },
  "entite_335": {
    "label": "MISC",
    "text": "buste de l'Am\ndu peuple",
    "jalons": [
      30822,
      30845
    ]
  },
  "entite_336": {
    "label": "PER",
    "text": "J.-J. Rous-",
    "jalons": [
      30898,
      30909
    ]
  },
  "entite_337": {
    "label": "PER",
    "text": "Brutus",
    "jalons": [
      30919,
      30925
    ]
  },
  "entite_338": {
    "label": "LOC",
    "text": "Lepeletier-Saint-Fargeau",
    "jalons": [
      30932,
      30956
    ]
  },
  "entite_339": {
    "label": "PER",
    "text": "Marat",
    "jalons": [
      31033,
      31038
    ]
  },
  "entite_340": {
    "label": "MISC",
    "text": "La Liberté",
    "jalons": [
      31066,
      31076
    ]
  },
  "entite_341": {
    "label": "LOC",
    "text": "Venette",
    "jalons": [
      31345,
      31352
    ]
  },
  "entite_342": {
    "label": "PER",
    "text": "Le Roy",
    "jalons": [
      31362,
      31368
    ]
  },
  "entite_343": {
    "label": "PER",
    "text": "Marat",
    "jalons": [
      31583,
      31588
    ]
  },
  "entite_344": {
    "label": "LOC",
    "text": "l’",
    "jalons": [
      31597,
      31599
    ]
  },
  "entite_345": {
    "label": "MISC",
    "text": "W..... pour servir de marraine",
    "jalons": [
      31650,
      31680
    ]
  },
  "entite_346": {
    "label": "LOC",
    "text": "Venette",
    "jalons": [
      31763,
      31770
    ]
  },
  "entite_347": {
    "label": "LOC",
    "text": "Compiègne",
    "jalons": [
      31923,
      31932
    ]
  },
  "entite_348": {
    "label": "LOC",
    "text": "Marat-sur-Oise",
    "jalons": [
      31945,
      31959
    ]
  },
  "entite_349": {
    "label": "MISC",
    "text": "Commune de Marat-sur-Oise",
    "jalons": [
      32142,
      32167
    ]
  },
  "entite_350": {
    "label": "MISC",
    "text": "Convention",
    "jalons": [
      32208,
      32218
    ]
  },
  "entite_351": {
    "label": "MISC",
    "text": "Convention",
    "jalons": [
      32311,
      32321
    ]
  },
  "entite_352": {
    "label": "PER",
    "text": "d’",
    "jalons": [
      32391,
      32393
    ]
  },
  "entite_353": {
    "label": "PER",
    "text": "Marat",
    "jalons": [
      32777,
      32782
    ]
  },
  "entite_354": {
    "label": "LOC",
    "text": "Compiègne",
    "jalons": [
      32875,
      32884
    ]
  },
  "entite_355": {
    "label": "MISC",
    "text": "République",
    "jalons": [
      33124,
      33134
    ]
  },
  "entite_356": {
    "label": "LOC",
    "text": "Compiègne",
    "jalons": [
      33315,
      33324
    ]
  },
  "entite_357": {
    "label": "PER",
    "text": "Marat",
    "jalons": [
      33401,
      33406
    ]
  },
  "entite_358": {
    "label": "PER",
    "text": "Le Pelletier",
    "jalons": [
      33410,
      33422
    ]
  },
  "entite_359": {
    "label": "LOC",
    "text": "Ré-",
    "jalons": [
      33457,
      33460
    ]
  },
  "entite_360": {
    "label": "PER",
    "text": "Raison",
    "jalons": [
      33536,
      33542
    ]
  },
  "entite_361": {
    "label": "PER",
    "text": "Capet",
    "jalons": [
      33684,
      33689
    ]
  },
  "entite_362": {
    "label": "ORG",
    "text": "l’",
    "jalons": [
      33731,
      33733
    ]
  },
  "entite_363": {
    "label": "ORG",
    "text": "Groupe de l’",
    "jalons": [
      33752,
      33764
    ]
  },
  "entite_364": {
    "label": "ORG",
    "text": "Groupe",
    "jalons": [
      33881,
      33887
    ]
  },
  "entite_365": {
    "label": "ORG",
    "text": "Groupe de citoyennes",
    "jalons": [
      33907,
      33927
    ]
  },
  "entite_366": {
    "label": "PER",
    "text": "Buste de Rousseau",
    "jalons": [
      34042,
      34059
    ]
  },
  "entite_367": {
    "label": "ORG",
    "text": "Groupe de musiciens",
    "jalons": [
      34270,
      34289
    ]
  },
  "entite_368": {
    "label": "MISC",
    "text": "Buste de MARAT",
    "jalons": [
      34295,
      34309
    ]
  },
  "entite_369": {
    "label": "ORG",
    "text": "Groupe de citoyennes",
    "jalons": [
      34550,
      34570
    ]
  },
  "entite_370": {
    "label": "LOC",
    "text": "Raison",
    "jalons": [
      34611,
      34617
    ]
  },
  "entite_371": {
    "label": "ORG",
    "text": "Groupe",
    "jalons": [
      34623,
      34629
    ]
  },
  "entite_372": {
    "label": "ORG",
    "text": "l’Ami",
    "jalons": [
      34661,
      34666
    ]
  },
  "entite_373": {
    "label": "MISC",
    "text": "Peuple",
    "jalons": [
      34670,
      34676
    ]
  },
  "entite_374": {
    "label": "PER",
    "text": "Buste de Pelletier Saint-Fargeau",
    "jalons": [
      34714,
      34746
    ]
  },
  "entite_375": {
    "label": "MISC",
    "text": "Z! vota",
    "jalons": [
      34800,
      34807
    ]
  },
  "entite_376": {
    "label": "MISC",
    "text": "l’immole",
    "jalons": [
      34841,
      34849
    ]
  },
  "entite_377": {
    "label": "ORG",
    "text": "Groupe de frères d'armes",
    "jalons": [
      34931,
      34955
    ]
  },
  "entite_378": {
    "label": "LOC",
    "text": "rue de la Fédération",
    "jalons": [
      34976,
      34996
    ]
  },
  "entite_379": {
    "label": "LOC",
    "text": "Saint-Jacques",
    "jalons": [
      35052,
      35065
    ]
  },
  "entite_380": {
    "label": "PER",
    "text": "Marat",
    "jalons": [
      35092,
      35097
    ]
  },
  "entite_381": {
    "label": "ORG",
    "text": "L’",
    "jalons": [
      35130,
      35132
    ]
  },
  "entite_382": {
    "label": "LOC",
    "text": "Succès",
    "jalons": [
      35326,
      35332
    ]
  },
  "entite_383": {
    "label": "MISC",
    "text": "Loi",
    "jalons": [
      35518,
      35521
    ]
  },
  "entite_384": {
    "label": "LOC",
    "text": "rue d'Orléans",
    "jalons": [
      35556,
      35569
    ]
  },
  "entite_385": {
    "label": "LOC",
    "text": "Hôtel de Ville",
    "jalons": [
      35585,
      35599
    ]
  },
  "entite_386": {
    "label": "LOC",
    "text": "République !",
    "jalons": [
      35786,
      35798
    ]
  },
  "entite_387": {
    "label": "PER",
    "text": "n’",
    "jalons": [
      35802,
      35804
    ]
  },
  "entite_388": {
    "label": "LOC",
    "text": "Ré-",
    "jalons": [
      36147,
      36150
    ]
  },
  "entite_389": {
    "label": "LOC",
    "text": "Raison",
    "jalons": [
      36195,
      36201
    ]
  },
  "entite_390": {
    "label": "LOC",
    "text": "Liberté",
    "jalons": [
      36209,
      36216
    ]
  },
  "entite_391": {
    "label": "LOC",
    "text": "Égalité",
    "jalons": [
      36225,
      36232
    ]
  },
  "entite_392": {
    "label": "LOC",
    "text": "Levèque",
    "jalons": [
      36249,
      36256
    ]
  },
  "entite_393": {
    "label": "PER",
    "text": "Pa-",
    "jalons": [
      36450,
      36453
    ]
  },
  "entite_394": {
    "label": "LOC",
    "text": "Îles âmes",
    "jalons": [
      36637,
      36646
    ]
  },
  "entite_395": {
    "label": "LOC",
    "text": "Liberté",
    "jalons": [
      36966,
      36973
    ]
  },
  "entite_396": {
    "label": "LOC",
    "text": "l’",
    "jalons": [
      36980,
      36982
    ]
  },
  "entite_397": {
    "label": "PER",
    "text": "Pelletier",
    "jalons": [
      36993,
      37002
    ]
  },
  "entite_398": {
    "label": "PER",
    "text": "Marat",
    "jalons": [
      37009,
      37014
    ]
  },
  "entite_399": {
    "label": "PER",
    "text": "Pelletier",
    "jalons": [
      37131,
      37140
    ]
  },
  "entite_400": {
    "label": "PER",
    "text": "Marat",
    "jalons": [
      37147,
      37152
    ]
  },
  "entite_401": {
    "label": "MISC",
    "text": "Révolution",
    "jalons": [
      37505,
      37515
    ]
  },
  "entite_402": {
    "label": "MISC",
    "text": "d’",
    "jalons": [
      37534,
      37536
    ]
  },
  "entite_403": {
    "label": "LOC",
    "text": "Raison",
    "jalons": [
      37649,
      37655
    ]
  },
  "entite_404": {
    "label": "LOC",
    "text": "l’",
    "jalons": [
      37858,
      37860
    ]
  },
  "entite_405": {
    "label": "LOC",
    "text": "République française",
    "jalons": [
      38065,
      38085
    ]
  },
  "entite_406": {
    "label": "PER",
    "text": "Eglise Saint-Antoine",
    "jalons": [
      38112,
      38132
    ]
  },
  "entite_407": {
    "label": "LOC",
    "text": "Ainour",
    "jalons": [
      38262,
      38268
    ]
  },
  "entite_408": {
    "label": "LOC",
    "text": "Partie",
    "jalons": [
      38281,
      38287
    ]
  },
  "entite_409": {
    "label": "MISC",
    "text": "d’",
    "jalons": [
      38422,
      38424
    ]
  },
  "entite_410": {
    "label": "LOC",
    "text": "l’",
    "jalons": [
      38440,
      38442
    ]
  },
  "entite_411": {
    "label": "PER",
    "text": "Louis XVI",
    "jalons": [
      38454,
      38463
    ]
  },
  "entite_412": {
    "label": "LOC",
    "text": "Compiègne",
    "jalons": [
      38566,
      38575
    ]
  },
  "entite_413": {
    "label": "PER",
    "text": "M. de Pron-",
    "jalons": [
      38658,
      38669
    ]
  },
  "entite_414": {
    "label": "LOC",
    "text": "nay",
    "jalons": [
      38672,
      38675
    ]
  },
  "entite_415": {
    "label": "MISC",
    "text": "SIRE",
    "jalons": [
      38698,
      38702
    ]
  },
  "entite_416": {
    "label": "MISC",
    "text": "ZLouie",
    "jalons": [
      38797,
      38803
    ]
  },
  "entite_417": {
    "label": "PER",
    "text": "Bienfaisant",
    "jalons": [
      38808,
      38819
    ]
  },
  "entite_418": {
    "label": "LOC",
    "text": "Compiègne",
    "jalons": [
      38866,
      38875
    ]
  },
  "entite_419": {
    "label": "PER",
    "text": "d’",
    "jalons": [
      38896,
      38898
    ]
  },
  "entite_420": {
    "label": "LOC",
    "text": "Sire",
    "jalons": [
      39061,
      39065
    ]
  },
  "entite_421": {
    "label": "LOC",
    "text": "Ou",
    "jalons": [
      39260,
      39262
    ]
  },
  "entite_422": {
    "label": "LOC",
    "text": "Sire",
    "jalons": [
      39264,
      39268
    ]
  },
  "entite_423": {
    "label": "LOC",
    "text": "Daignez",
    "jalons": [
      39494,
      39501
    ]
  },
  "entite_424": {
    "label": "LOC",
    "text": "Sire",
    "jalons": [
      39503,
      39507
    ]
  },
  "entite_425": {
    "label": "PER",
    "text": "Roy",
    "jalons": [
      39567,
      39570
    ]
  },
  "entite_426": {
    "label": "LOC",
    "text": "Puisse",
    "jalons": [
      39635,
      39641
    ]
  },
  "entite_427": {
    "label": "LOC",
    "text": "Sire",
    "jalons": [
      39643,
      39647
    ]
  },
  "entite_428": {
    "label": "LOC",
    "text": "Compiègne",
    "jalons": [
      39665,
      39674
    ]
  },
  "entite_429": {
    "label": "PER",
    "text": "Puisse",
    "jalons": [
      39721,
      39727
    ]
  },
  "entite_430": {
    "label": "MISC",
    "text": "Votre\nMajesté",
    "jalons": [
      39775,
      39788
    ]
  },
  "entite_431": {
    "label": "LOC",
    "text": "luy",
    "jalons": [
      39804,
      39807
    ]
  },
  "entite_432": {
    "label": "LOC",
    "text": "Sire",
    "jalons": [
      39941,
      39945
    ]
  },
  "entite_433": {
    "label": "MISC",
    "text": "Vostre Majesté",
    "jalons": [
      40037,
      40051
    ]
  },
  "entite_434": {
    "label": "MISC",
    "text": "Doit-on",
    "jalons": [
      40086,
      40093
    ]
  },
  "entite_435": {
    "label": "LOC",
    "text": "Compiègne",
    "jalons": [
      40157,
      40166
    ]
  },
  "entite_436": {
    "label": "PER",
    "text": "Regi",
    "jalons": [
      40244,
      40248
    ]
  },
  "entite_437": {
    "label": "PER",
    "text": "Vatout",
    "jalons": [
      40292,
      40298
    ]
  },
  "entite_438": {
    "label": "PER",
    "text": "Chéteau de Compiègne",
    "jalons": [
      40303,
      40323
    ]
  },
  "entite_439": {
    "label": "PER",
    "text": "s’",
    "jalons": [
      40753,
      40755
    ]
  },
  "entite_440": {
    "label": "MISC",
    "text": "À\nle cas",
    "jalons": [
      40858,
      40866
    ]
  },
  "entite_441": {
    "label": "PER",
    "text": "s’",
    "jalons": [
      40870,
      40872
    ]
  },
  "entite_442": {
    "label": "PER",
    "text": "Illustre Bossuet",
    "jalons": [
      40884,
      40900
    ]
  },
  "entite_443": {
    "label": "ORG",
    "text": "FIN",
    "jalons": [
      40970,
      40973
    ]
  },
  "entite_444": {
    "label": "MISC",
    "text": "D\n\n \n\nus A",
    "jalons": [
      41018,
      41028
    ]
  }
}